CHANGELOG.rst
LICENSE
MANIFEST.in
README.rst
setup.py
cacheback/__init__.py
cacheback/base.py
cacheback/decorators.py
cacheback/function.py
cacheback/queryset.py
cacheback/tasks.py
django_cacheback_pozytywnie.egg-info/PKG-INFO
django_cacheback_pozytywnie.egg-info/SOURCES.txt
django_cacheback_pozytywnie.egg-info/dependency_links.txt
django_cacheback_pozytywnie.egg-info/requires.txt
django_cacheback_pozytywnie.egg-info/top_level.txt