Metadata-Version: 1.1
Name: django-cacheback-pozytywnie
Version: 0.7
Summary: Caching library for Django that uses Celery to refresh cache items asynchronously
Home-page: https://github.com/codeinthehole/django-cacheback
Author: David Winterbottom
Author-email: david.winterbottom@gmail.com
License: MIT
Platform: UNKNOWN
Classifier: Environment :: Web Environment
Classifier: Framework :: Django
Classifier: Intended Audience :: Developers
Classifier: License :: OSI Approved :: BSD License
Classifier: Operating System :: Unix
Classifier: Programming Language :: Python
